DSLTranslation/DSLTranslation.py
DSLTranslation/__init__.py
DSLTranslation-0.1.1.dist-info/LICENSE
DSLTranslation-0.1.1.dist-info/METADATA
DSLTranslation-0.1.1.dist-info/WHEEL
DSLTranslation-0.1.1.dist-info/top_level.txt
DSLTranslation-0.1.1.dist-info/RECORD
