Metadata-Version: 2.1
Name: DSLTranslation
Version: 0.1.1
Summary: Translation of natural Domain Specific Language (DSL) commands into code.
Home-page: https://github.com/antononcube/Python-packages/tree/main/DSLTranslation
Author: Anton Antonov
Author-email: antononcube@posteo.net
Keywords: dsl,parser,interpreter,code generation,multi-language,nlp
Classifier: Intended Audience :: Science/Research
Classifier: Intended Audience :: Developers
Classifier: Programming Language :: Python :: 3
Classifier: License :: OSI Approved :: BSD License
Classifier: Intended Audience :: Science/Research
Classifier: Intended Audience :: Developers
Classifier: Operating System :: OS Independent
Requires-Python: >=3.7
License-File: LICENSE
Requires-Dist: pyperclip
